sksurv/__init__.py
sksurv/base.py
sksurv/column.py
sksurv/compare.py
sksurv/docstrings.py
sksurv/exceptions.py
sksurv/functions.py
sksurv/metrics.py
sksurv/nonparametric.py
sksurv/preprocessing.py
sksurv/testing.py
sksurv/util.py
sksurv/bintrees/__init__.py
sksurv/bintrees/_binarytrees.cpython-312-x86_64-linux-gnu.so
sksurv/datasets/__init__.py
sksurv/datasets/base.py
sksurv/datasets/data/GBSG2.arff
sksurv/datasets/data/actg320.arff
sksurv/datasets/data/bmt.arff
sksurv/datasets/data/breast_cancer_GSE7390-metastasis.arff
sksurv/datasets/data/cgvhd.arff
sksurv/datasets/data/flchain.arff
sksurv/datasets/data/veteran.arff
sksurv/datasets/data/whas500.arff
sksurv/ensemble/__init__.py
sksurv/ensemble/_coxph_loss.cpython-312-x86_64-linux-gnu.so
sksurv/ensemble/boosting.py
sksurv/ensemble/forest.py
sksurv/ensemble/survival_loss.py
sksurv/io/__init__.py
sksurv/io/arffread.py
sksurv/io/arffwrite.py
sksurv/kernels/__init__.py
sksurv/kernels/_clinical_kernel.cpython-312-x86_64-linux-gnu.so
sksurv/kernels/clinical.py
sksurv/linear_model/__init__.py
sksurv/linear_model/_coxnet.cpython-312-x86_64-linux-gnu.so
sksurv/linear_model/aft.py
sksurv/linear_model/coxnet.py
sksurv/linear_model/coxph.py
sksurv/meta/__init__.py
sksurv/meta/base.py
sksurv/meta/ensemble_selection.py
sksurv/meta/stacking.py
sksurv/svm/__init__.py
sksurv/svm/_minlip.cpython-312-x86_64-linux-gnu.so
sksurv/svm/_prsvm.cpython-312-x86_64-linux-gnu.so
sksurv/svm/minlip.py
sksurv/svm/naive_survival_svm.py
sksurv/svm/survival_svm.py
sksurv/tree/__init__.py
sksurv/tree/_criterion.cpython-312-x86_64-linux-gnu.so
sksurv/tree/tree.py
scikit_survival-0.25.0.dist-info/METADATA
scikit_survival-0.25.0.dist-info/WHEEL
scikit_survival-0.25.0.dist-info/top_level.txt
scikit_survival-0.25.0.dist-info/RECORD
scikit_survival-0.25.0.dist-info/licenses/COPYING
