Metadata-Version: 2.4
Name: scikit-survival
Version: 0.25.0
Summary: Survival analysis built on top of scikit-learn
Author-email: Sebastian Pölsterl <sebp@k-d-w.org>
License-Expression: GPL-3.0-or-later
Project-URL: Homepage, https://github.com/sebp/scikit-survival
Project-URL: Documentation, https://scikit-survival.readthedocs.io
Project-URL: Source Code, https://github.com/sebp/scikit-survival
Project-URL: Bug Tracker, https://github.com/sebp/scikit-survival/issues
Project-URL: Release Notes, https://scikit-survival.readthedocs.io/en/latest/release_notes.html
Classifier: Development Status :: 4 - Beta
Classifier: Intended Audience :: Science/Research
Classifier: Intended Audience :: Developers
Classifier: Operating System :: MacOS
Classifier: Operating System :: Microsoft :: Windows
Classifier: Operating System :: POSIX
Classifier: Programming Language :: C++
Classifier: Programming Language :: Cython
Classifier: Programming Language :: Python
Classifier: Programming Language :: Python :: 3
Classifier: Programming Language :: Python :: 3.10
Classifier: Programming Language :: Python :: 3.11
Classifier: Programming Language :: Python :: 3.12
Classifier: Programming Language :: Python :: 3.13
Classifier: Topic :: Software Development
Classifier: Topic :: Scientific/Engineering
Requires-Python: >=3.10
License-File: COPYING
Requires-Dist: ecos
Requires-Dist: joblib
Requires-Dist: numexpr
Requires-Dist: numpy
Requires-Dist: osqp<1.0.0,>=0.6.3
Requires-Dist: pandas>=1.4.0
Requires-Dist: scipy>=1.3.2
Requires-Dist: scikit-learn<1.8,>=1.6.1
Dynamic: license-file
